mkdocs_content_tabs/__init__.py
mkdocs_content_tabs/plugin.py
mkdocs_content_tabs/utils.py
mkdocs_content_tabs-1.0.5.dist-info/LICENSE
mkdocs_content_tabs-1.0.5.dist-info/METADATA
mkdocs_content_tabs-1.0.5.dist-info/WHEEL
mkdocs_content_tabs-1.0.5.dist-info/entry_points.txt
mkdocs_content_tabs-1.0.5.dist-info/top_level.txt
mkdocs_content_tabs-1.0.5.dist-info/RECORD
