Metadata-Version: 2.1
Name: mkdocs-content-tabs
Version: 1.0.5
Summary: A simple plugin that converts Obsidian content tabs and converts them into mkdocs supported content tabs.
Author-email: epleone <epleone@qq.com>
License: MIT
Project-URL: homepage, https://github.com/epleone/mkdocs-content-tabs
Keywords: mkdocs,mkdocs-plugin,markdown,obsidian,content-tabs
Classifier: Development Status :: 5 - Production/Stable
Classifier: License :: OSI Approved :: MIT License
Classifier: Programming Language :: Python
Classifier: Programming Language :: Python :: 3
Classifier: Programming Language :: Python :: 3 :: Only
Classifier: Topic :: Documentation
Classifier: Topic :: Software Development :: Documentation
Requires-Python: >=3.8
License-File: LICENSE
Requires-Dist: mkdocs>=1
